codesearch_ai
