Metadata-Version: 2.1
Name: codesearch-ai
Version: 0.1.0
Summary: Chat with your current directory's files using a local or API LLM.
Home-page: https://github.com/galatea-associates/codesearch_ai
Author: Galatea Associates
Author-email: careers@galatea-associates.com
License: MIT
Platform: UNKNOWN
Classifier: Programming Language :: Python :: 3
Classifier: License :: OSI Approved :: MIT License
Classifier: Operating System :: OS Independent
Requires-Python: >=3.6
License-File: LICENSE
